doc/make.py
doc/source/conf.py
examples/cc/00-simple.py
examples/cc/01-ccsd_t.py
examples/cc/02-df-ccsd_t.py
examples/cc/20-raman.py
examples/cc/21-ir.py
examples/cc/30-jacobian.py
examples/dft/00-simple.py
examples/dft/01-DFT+U.py
examples/dft/02-uks.py
examples/fci/00-simple.py
examples/fci/10-nac.py
examples/gto/00-simple.py
examples/gto/20-optimize_exps.py
examples/gw/01-rpa.py
examples/gw/02-oo-rpa.py
examples/gw/03-rpa-geomopt-with-pyberny.py
examples/mp/00-simple.py
examples/mp/10-oomp2.py
examples/pbc/dft/00-simple.py
examples/pbc/dft/01-krks.py
examples/pbc/dft/02-krks-hessian.py
examples/pbc/gto/00-simple.py
examples/pbc/scf/00-simple.py
examples/pbc/scf/01-krhf.py
examples/pbc/scf/02-krhf-hessian.py
examples/pbc/scf/10-stress.py
examples/scf/00-simple.py
examples/scf/01-hessian.py
examples/scf/02-uhf.py
examples/scf/03-rohf.py
examples/scf/10-polarizability.py
examples/scf/11-born_charge.py
examples/scf/12-raman.py
examples/scf/21-ir.py
examples/scf/31-hessian_vector_product.py
examples/tdscf/00-cis_nuc_grad.py
examples/tdscf/10-cis_nac.py
examples/tdscf/11-cis_nac_hellman.py
pyscfad/__init__.py
pyscfad/implicit_diff.py
pyscfad/util.py
pyscfad/version.py
pyscfad/_src/__init__.py
pyscfad/_src/_config.py
pyscfad/_src/implicit_diff.py
pyscfad/_src/scipy/__init__.py
pyscfad/_src/scipy/linalg.py
pyscfad/_src/scipy/sparse/__init__.py
pyscfad/_src/scipy/sparse/linalg.py
pyscfad/ao2mo/__init__.py
pyscfad/ao2mo/_ao2mo.py
pyscfad/ao2mo/_ao2mo_opt.py
pyscfad/ao2mo/addons.py
pyscfad/ao2mo/incore.py
pyscfad/backend/__init__.py
pyscfad/backend/config.py
pyscfad/backend/numpy.py
pyscfad/backend/ops.py
pyscfad/backend/pytree.py
pyscfad/backend/_common/__init__.py
pyscfad/backend/_common/core.py
pyscfad/backend/_common/pytree.py
pyscfad/backend/_cupy/__init__.py
pyscfad/backend/_cupy/core.py
pyscfad/backend/_jax/__init__.py
pyscfad/backend/_jax/core.py
pyscfad/backend/_jax/pytree.py
pyscfad/backend/_jax/lax/__init__.py
pyscfad/backend/_jax/lax/linalg.py
pyscfad-0.2.0.dist-info/licenses/LICENSE
pyscfad-0.2.0.dist-info/METADATA
pyscfad-0.2.0.dist-info/WHEEL
pyscfad-0.2.0.dist-info/top_level.txt
pyscfad-0.2.0.dist-info/RECORD
