Metadata-Version: 2.4
Name: pyscfad
Version: 0.2.0
Summary: PySCF with autodiff
Author-email: Xing Zhang <zhangxing.nju@gmail.com>
License: Apache-2.0
Project-URL: Homepage, https://github.com/fishjojo/pyscfad
Classifier: Development Status :: 3 - Alpha
Classifier: Topic :: Scientific/Engineering
Classifier: Intended Audience :: Science/Research
Classifier: Programming Language :: Python :: 3.11
Classifier: Programming Language :: Python :: 3.12
Classifier: Programming Language :: Python :: 3.13
Classifier: Programming Language :: Python :: 3.14
Requires-Python: >=3.11
License-File: LICENSE
Requires-Dist: jax<0.9,>=0.7.1
Requires-Dist: pyscfadlib>=0.1.11
Requires-Dist: pyscf>=2.3
Requires-Dist: pyscf-properties
Provides-Extra: cuda12
Requires-Dist: jax[cuda12]<0.9,>=0.7.1; extra == "cuda12"
Requires-Dist: pyscfad-cuda12-plugin[with_cuda]>=0.1.11; extra == "cuda12"
Dynamic: license-file
